pants_jupyter_plugin/__init__.py
pants_jupyter_plugin/cache.py
pants_jupyter_plugin/download.py
pants_jupyter_plugin/env.py
pants_jupyter_plugin/lock.py
pants_jupyter_plugin/pex.py
pants_jupyter_plugin/plugin.py
pants_jupyter_plugin-0.0.6.dist-info/LICENSE
pants_jupyter_plugin-0.0.6.dist-info/WHEEL
pants_jupyter_plugin-0.0.6.dist-info/METADATA
pants_jupyter_plugin-0.0.6.dist-info/RECORD
