Metadata-Version: 2.1
Name: pants-jupyter-plugin
Version: 0.0.6
Summary: Jupyter support for Pants projects and PEX files.
Home-page: https://github.com/pantsbuild/pants-jupyter-plugin
Author: The Pants developers
Author-email: pantsbuild@gmail.com
Requires-Python: >=3.6,<3.11
Classifier: Development Status :: 4 - Beta
Classifier: Intended Audience :: Developers
Classifier: Intended Audience :: Science/Research
Classifier: License :: OSI Approved :: Apache Software License
Classifier: Programming Language :: Python
Classifier: Programming Language :: Python :: 3
Classifier: Programming Language :: Python :: 3.6
Classifier: Programming Language :: Python :: 3.7
Classifier: Programming Language :: Python :: 3.8
Classifier: Programming Language :: Python :: 3.9
Classifier: Programming Language :: Python :: 3.10
Classifier: Framework :: IPython
Requires-Dist: dataclasses==0.8; python_version == '3.6'
Requires-Dist: filelock>=3.0
Requires-Dist: ipython>=5.5.0,<8.0
Requires-Dist: ipywidgets>=7.0.0,<8.0
Requires-Dist: nest_asyncio~=1.5.1
Requires-Dist: requests>=2.22.0
Requires-Dist: twitter.common.contextutil~=0.3.11
Requires-Dist: xdg>=5.0.0,<6.0
Project-URL: Changelog, https://github.com/pantsbuild/pants-jupyter-plugin/blob/main/CHANGES.md
